bpf4-1.14.0.dist-info/RECORD
bpf4-1.14.0.dist-info/WHEEL
bpf4-1.14.0.dist-info/top_level.txt
bpf4-1.14.0.dist-info/METADATA
bpf4-1.14.0.dist-info/licenses/LICENSE.md
bpf4/arraytools.py
bpf4/plot.py
bpf4/config.py
bpf4/__init__.pyi
bpf4/util.py
bpf4/pyinterp.py
bpf4/csvtools.py
bpf4/__init__.py
bpf4/bench.py
bpf4/api.py
bpf4/py.typed
bpf4/core.abi3.so
bpf4/tests.py
bpf4/core.pyx
