Metadata-Version: 2.4
Name: bpf4
Version: 1.14.0
Summary: Piece-wise interpolation and lazy evaluation in cython
Author-email: Eduardo Moguillansky <eduardo.moguillansky@gmail.com>
License: GPLv3
Project-URL: Homepage, https://github.com/gesellkammer/bpf4
Classifier: Programming Language :: Python :: 3
Classifier: Operating System :: OS Independent
Classifier: Topic :: Multimedia :: Sound/Audio
Requires-Python: >=3.10
License-File: LICENSE.md
Requires-Dist: numpy>=2.0
Requires-Dist: matplotlib
Requires-Dist: scipy
Requires-Dist: visvalingamwyatt
Dynamic: license-file
Dynamic: requires-python
